privacera_shield/PluginAccessRequestEncryptor.py
privacera_shield/__init__.py
privacera_shield/backend.py
privacera_shield/client.py
privacera_shield/core.py
privacera_shield/encryption.py
privacera_shield/exception.py
privacera_shield/interceptor.py
privacera_shield/interceptor_setup.py
privacera_shield/langchain_callback.py
privacera_shield/langchain_method_interceptor.py
privacera_shield/langchain_streaming_interceptor.py
privacera_shield/message.py
privacera_shield/milvus_method_interceptor.py
privacera_shield/model.py
privacera_shield/opensearch_method_interceptor.py
privacera_shield/util.py
privacera_shield-1.1.13.dist-info/METADATA
privacera_shield-1.1.13.dist-info/WHEEL
privacera_shield-1.1.13.dist-info/licenses/LICENSE
privacera_shield-1.1.13.dist-info/RECORD
